{
  "army_building": [
    {"level": "1",      "troop_unlocked": "Minion",      "build_cost": "300,000",        "build_time": "4h",       "th": "7"},
    {"level": "2",      "troop_unlocked": "Hog Rider",   "build_cost": "600,000",        "build_time": "12h",      "th": "7"},
    {"level": "3",      "troop_unlocked": "Valkyrie",    "build_cost": "900,000",        "build_time": "18h",      "th": "8"},
    {"level": "4",      "troop_unlocked": "Golem",       "build_cost": "1,300,000",      "build_time": "1d",       "th": "8"},
    {"level": "5",      "troop_unlocked": "Witch",       "build_cost": "2,000,000",      "build_time": "2d",       "th": "9"},
    {"level": "6",      "troop_unlocked": "Lava Hound",  "build_cost": "2,500,000",      "build_time": "3d",       "th": "9"},
    {"level": "7",      "troop_unlocked": "Bowler",      "build_cost": "3,000,000",      "build_time": "5d",       "th": "10"},
    {"level": "8",      "troop_unlocked": "Ice Golem",   "build_cost": "4,000,000",      "build_time": "9d",       "th": "11"},
    {"level": "9",      "troop_unlocked": "Headhunter",  "build_cost": "7,500,000",      "build_time": "13d",      "th": "12"}
  ]
}